lyrix/__init__.py
lyrix/assets/icon.ico
lyrix/assets/icon.png
lyrix/assets/screenshot.jpg
lyrix/lyrics.json
lyrix/lyrics.py
lyrix-0.1.0.dist-info/LICENSE.md
lyrix-0.1.0.dist-info/WHEEL
lyrix-0.1.0.dist-info/METADATA
lyrix-0.1.0.dist-info/RECORD
