Metadata-Version: 2.1
Name: lyrix
Version: 0.1.0
Summary: The ultimate lyrics app for tiling window managers.
License: GPL-3.0-or-later
Author: Daniel Rose
Author-email: daniel@whitehatcat.net
Requires-Python: >=3.8,<4.0
Classifier: License :: OSI Approved :: GNU General Public License v3 or later (GPLv3+)
Classifier: Programming Language :: Python :: 3
Classifier: Programming Language :: Python :: 3.8
Requires-Dist: beautifulsoup4 (>=4.9.3,<5.0.0)
Requires-Dist: certifi (>=2020.6.20,<2021.0.0)
Requires-Dist: chardet (>=3.0.4,<4.0.0)
Requires-Dist: idna (>=2.10,<3.0)
Requires-Dist: lyricsgenius (>=2.0.2,<3.0.0)
Requires-Dist: requests (>=2.24.0,<3.0.0)
Requires-Dist: six (>=1.15.0,<2.0.0)
Requires-Dist: spotipy (>=2.16.1,<3.0.0)
Requires-Dist: urllib3 (>=1.25.11,<2.0.0)
